irvy/__init__.py
irvy/irvy.py
irvy/generators/PlaywrightGenerator.py
irvy/generators/SeleniumGenerator.py
irvy/generators/__init__.py
irvy/utils/__init__.py
irvy/utils/configuration.py
irvy-1.0.5.dist-info/METADATA
irvy-1.0.5.dist-info/WHEEL
irvy-1.0.5.dist-info/entry_points.txt
irvy-1.0.5.dist-info/top_level.txt
irvy-1.0.5.dist-info/RECORD
