Metadata-Version: 2.1
Name: irvy
Version: 1.0.5
Summary: A brief description of your project
